provinceitaliane
