Metadata-Version: 1.0
Name: django-provinceitaliane
Version: 0.1.1
Summary: Province e Regioni Italiane for Django
Home-page: http://code.google.com/p/django-provinceitaliane/
Author: Francesco Facconi
Author-email: UNKNOWN
License: UNKNOWN
Platform: UNKNOWN
